lyberry_api/__init__.py
lyberry_api/account.py
lyberry_api/api.py
lyberry_api/channel.py
lyberry_api/claim.py
lyberry_api/collection.py
lyberry_api/comment.py
lyberry_api/conf.toml
lyberry_api/preferences.py
lyberry_api/pub.py
lyberry_api/settings.py
lyberry_api-0.2.2.dist-info/LICENSE.txt
lyberry_api-0.2.2.dist-info/METADATA
lyberry_api-0.2.2.dist-info/WHEEL
lyberry_api-0.2.2.dist-info/top_level.txt
lyberry_api-0.2.2.dist-info/RECORD
