Metadata-Version: 2.1
Name: lyberry-api
Version: 0.2.2
Summary: An easier way to interact with lbrynet using python
Home-page: https://git.tristans.cloud/tristan/lyberry_api
Author: MyBeansAreBaked
Author-email: tristan@tristans.cloud
License: GPLv3+
Platform: UNKNOWN
Classifier: Programming Language :: Python :: 3
Classifier: License :: OSI Approved :: GNU General Public License v3 or later (GPLv3+)
Classifier: Operating System :: OS Independent
Requires-Python: >=3.6
License-File: LICENSE.txt
Requires-Dist: requests
Requires-Dist: toml
Requires-Dist: appdirs
